pynotices/__init__.py
pynotices/pynotice.py
pynotices-1.1.dist-info/METADATA
pynotices-1.1.dist-info/WHEEL
pynotices-1.1.dist-info/top_level.txt
pynotices-1.1.dist-info/RECORD
