Metadata-Version: 2.1
Name: pynotices
Version: 1.1
Summary: The information notification module developed by python3 includes nailing, email, enterprise wechat and flybook
Home-page: https://github.com/ZhongQingHao/pynotice
Author: SpiderZhong
Author-email: 5805461@qq.com
Maintainer: zhongqinghao
Maintainer-email: root@ihack.cc
License: MIT
Platform: all
Classifier: Operating System :: OS Independent
Classifier: License :: OSI Approved :: BSD License
Classifier: Programming Language :: Python :: 3
Classifier: Programming Language :: Python :: 3.4
Classifier: Programming Language :: Python :: 3.5
Classifier: Programming Language :: Python :: 3.6
Classifier: Programming Language :: Python :: 3.7
Classifier: Programming Language :: Python :: 3.8
Classifier: Topic :: Software Development :: Libraries
Requires-Dist: requests
